[
    {
        "Question": "**\nQuestion 1 :** ```Expert du déguisement et de l’infiltration, mon rôle est de recueillir des informations dans un pays au bénéfice d’une puissance étrangère\n```",
        "Response": "espion",
        "Hint": "**\nIndice :** ```Agent secret\n```" 
    },

    {
       "Question": "**\nQuestion 2 :** ```Je suis une personne qui voit dans l’avenir, je suis un...\n```", 
       "Response": "voyant",
       "Hint": "**\nIndice:** ```Synonymes de : devin, extralucide, spirite\n```"
    },

    {
        "Question": "**\nQuestion 3 :**  ```J’exerce la forme la plus cruelle des censures. Mon Job c’est d’hôter des vies, je suis un...\n```", 
        "Response": "Assassin",
        "Hint": "**\nIndice :** ```Personne qui commet un meurtre avec préméditation ou guet-apens\n```"
     },

     {
        "Question": "**\nQuestion 4 :** ```Nous sommes un, nous sommes même, nous prenons des horizons divers, mais nous sommes issus du même arbre, et notre lien ne pourra jamais changer\n```", 
        "Response": "Famille",
        "Hint": "**\nIndice :** ```Synonyme : Ensemble des personnes vivant sous le même toit\n``` "
     },

     {
         "Question": "**\nQuestion 5 :** ```Alors avez vous trouver de quelle manga il s'agit ?\n```", 
         "Response": "spy family",
         "Hint": "https://static.wikia.nocookie.net/spy-x-family9171/images/d/da/Bond_Forger_Anime.png/revision/latest?cb=20221015174857"
      }
]